setup.py
django_support.egg-info/PKG-INFO
django_support.egg-info/SOURCES.txt
django_support.egg-info/dependency_links.txt
django_support.egg-info/top_level.txt
support/__init__.py
support/functions.py
support/settings.py
support/forms/__init__.py
support/forms/forms.py
support/forms/processing.py
support/forms/widgets.py
support/forms/html5/__init__.py
support/forms/html5/fields.py
support/forms/html5/widgets.py
support/templatetags/__init__.py
support/templatetags/form_tags.py
support/templatetags/support_tags.py