Metadata-Version: 1.0
Name: django-support
Version: 0.2
Summary: Support filters/tags/etc. for django.
Home-page: https://github.com/chrisdrackett/django-support
Author: Chris Drackett
Author-email: chris@drackett.com
License: BSD
Platform: UNKNOWN
Classifier: Environment :: Web Environment
Classifier: Intended Audience :: Developers
Classifier: Operating System :: OS Independent
Classifier: Programming Language :: Python
Classifier: Framework :: Django
